setup.py
funniest_pipname/__init__.py
funniest_pipname.egg-info/PKG-INFO
funniest_pipname.egg-info/SOURCES.txt
funniest_pipname.egg-info/dependency_links.txt
funniest_pipname.egg-info/not-zip-safe
funniest_pipname.egg-info/top_level.txt